cybernews/__init__.py
cybernews/cybernews.py
test/__init__.py
test/unit.py
utils/__init__.py
utils/extractor.py
utils/performance.py
utils/sorting.py
cybernews-1.1.2.dist-info/LICENSE
cybernews-1.1.2.dist-info/METADATA
cybernews-1.1.2.dist-info/WHEEL
cybernews-1.1.2.dist-info/top_level.txt
cybernews-1.1.2.dist-info/RECORD
