Metadata-Version: 2.1
Name: cybernews
Version: 1.1.2
Summary: Get the latest Cyber Security updates curated from different sources under one roof.
Author: GhoulBond
Author-email: hitesh22rana@gmail.com
Keywords: python,web scraping,news,cyber news,hacker news,hacking,cyber,free,open source,latest news,project,api,REST-API,cyber security,cybersecurity,updates,news,cyber attacks,cyber threats,online security
Classifier: Development Status :: 1 - Planning
Classifier: Intended Audience :: Developers
Classifier: Programming Language :: Python :: 3
Classifier: Operating System :: Unix
Classifier: Operating System :: MacOS :: MacOS X
Classifier: Operating System :: Microsoft :: Windows
License-File: LICENSE
